[
    {
        "access": "ＪＲ京浜東北線・宇都宮線・高崎線・湘南新宿ライン浦和 徒歩12分<br>ＪＲ京浜東北線・宇都宮線・高崎線・湘南新宿ライン浦和 徒歩13分", 
        "access_codes": [
            2196, 
            2105
        ], 
        "access_int": 11, 
        "address": "埼玉県さいたま市浦和区常盤二丁目32番2他（地番）", 
        "area_id": 8, 
        "catch_copy": "県都・浦和の邸宅地に誕生。", 
        "comment": "新たな商業施設と北口の誕生で発展を続けるJR「浦和」駅・文教の薫り高き常盤に開放感溢れる邸宅が誕生。", 
        "division_type": 1, 
        "gross_area": "71.46 ～ 83.35m&sup2; (※トランクルーム面積0.60㎡～0.93㎡含む)", 
        "gross_area_float": 83.35, 
        "houses": "42戸 (非分譲住戸1戸含む)", 
        "houses_int": 42, 
        "image_pc_url": "/image_files/estate_basics/proudtop_pc/00000851/225_140.jpg", 
        "layout": "3LDK ～ 4LDK", 
        "prefecture": "埼玉県", 
        "published_at": 1450665791, 
        "structure_code": "010851", 
        "structure_id": 851, 
        "structure_name": "プラウド浦和常盤<br>カトラージュ", 
        "structure_url": "http://www.proud-web.jp/mansion/urawa-tokiwa2"
    }, 
    {
        "access": "ＪＲ総武線津田沼 徒歩7分<br>新京成電鉄新京成線新津田沼 徒歩5分", 
        "access_codes": [
            2161, 
            2256
        ], 
        "access_int": 5, 
        "address": "千葉県船橋市前原東一丁目209-12（地番）", 
        "area_id": 7, 
        "catch_copy": "いよいよ資料請求受付開始！", 
        "comment": "ＪＲ総武線快速・総武線「津田沼」駅徒歩７分。大型商業施設が集う駅北口の閑静な戸建中心の住宅地に誕生", 
        "division_type": 1, 
        "gross_area": "72.38 ～ 87.45m&sup2; (非分譲住戸除く)", 
        "gross_area_float": 87.45, 
        "houses": "49戸 (うち非分譲住戸3戸)", 
        "houses_int": 49, 
        "image_pc_url": "/image_files/estate_basics/proudtop_pc/00000877/PC.jpg", 
        "layout": "2LDK+S ～ 4LDK", 
        "prefecture": "千葉県", 
        "published_at": 1450665413, 
        "structure_code": "010877", 
        "structure_id": 877, 
        "structure_name": "プラウド津田沼前原東", 
        "structure_url": "http://www.proud-web.jp/mansion/tsudanuma49/"
    }, 
    {
        "access": "都営地下鉄大江戸線練馬春日町 徒歩7分<br>都営地下鉄大江戸線光が丘 徒歩12分", 
        "access_codes": [
            2358
        ], 
        "access_int": 7, 
        "address": "東京都練馬区春日町６丁目2879番1（地番）", 
        "area_id": 3, 
        "catch_copy": "駅近・南側が開けた呼吸する邸", 
        "comment": "「練馬春日町」駅徒歩7分。美しい桜並木アプローチ、南側が開けた陽光・通風に恵まれた「呼吸する邸」誕生", 
        "division_type": 1, 
        "gross_area": "70.00 ～ 83.82m&sup2;", 
        "gross_area_float": 83.82, 
        "houses": "57戸 (非分譲住戸7戸含む)", 
        "houses_int": 57, 
        "image_pc_url": "/image_files/estate_basics/proudtop_pc/00000859/icon-225_140.jpg", 
        "layout": "3LDK ～ 4LDK", 
        "prefecture": "東京都", 
        "published_at": 1448433109, 
        "structure_code": "010859", 
        "structure_id": 859, 
        "structure_name": "プラウド練馬春日町<br>サンクアージュ", 
        "structure_url": "http://www.proud-web.jp/mansion/nerimakasuga57/"
    }, 
    {
        "access": "京王電鉄京王線府中 徒歩1分<br>", 
        "access_codes": [
            2301
        ], 
        "access_int": 1, 
        "address": "東京都府中市宮町一丁目100番（地番）", 
        "area_id": 5, 
        "catch_copy": "駅直結1分。複合再開発、始動。", 
        "comment": "京王線「府中」駅へ、ペデストリアンデッキ直結1分。商・公・医・住複合再開発プロジェクト、始動。", 
        "division_type": 1, 
        "gross_area": "63.01 ～ 102.51m&sup2;", 
        "gross_area_float": 102.51, 
        "houses": "138戸 (非分譲27戸含む)", 
        "houses_int": 138, 
        "image_pc_url": "/image_files/estate_basics/proudtop_pc/00000860/225_140.jpg", 
        "layout": "2LDK ～ 4LDK", 
        "prefecture": "東京都", 
        "published_at": 1445311221, 
        "structure_code": "010860", 
        "structure_id": 860, 
        "structure_name": "プラウド府中ステーション<br>アリーナ", 
        "structure_url": "http://www.proud-web.jp/mansion/fuchu-ekimae/"
    }, 
    {
        "access": "ＪＲ総武線下総中山 徒歩6分<br>京成電鉄京成本線京成中山 徒歩10分", 
        "access_codes": [
            2199, 
            2251
        ], 
        "access_int": 6, 
        "address": "千葉県市川市鬼高二丁目1240番93他", 
        "area_id": 7, 
        "catch_copy": "総武線駅徒歩6分、全144邸", 
        "comment": "総武線「下総中山」駅徒歩6分「ニッケコルトンプラザ」徒歩8分の地に周囲でも希少な144邸の規模で誕生", 
        "division_type": 1, 
        "gross_area": "65.73 ～ 100.59m&sup2;", 
        "gross_area_float": 100.59, 
        "houses": "144戸", 
        "houses_int": 144, 
        "image_pc_url": "/image_files/estate_basics/proudtop_pc/00000858/banner_pc.jpg", 
        "layout": "3LDK ～ 4LDK", 
        "prefecture": "千葉県", 
        "published_at": 1445308048, 
        "structure_code": "010858", 
        "structure_id": 858, 
        "structure_name": "プラウド下総中山<br>ディアージュ", 
        "structure_url": "http://www.proud-web.jp/mansion/shimousanakayama"
    }, 
    {
        "access": "ＪＲ東海道線・上野東京ライン戸塚バス約5分舞岡中学校前バス停より 徒歩2分<br>ＪＲ横須賀線・総武線快速、湘南新宿ライン戸塚バス約5分舞岡中学校前バス停より 徒歩2分", 
        "access_codes": [
            2171, 
            2179
        ], 
        "access_int": 2, 
        "address": "神奈川県横浜市戸塚区舞岡町184-1　他4筆(地番)", 
        "area_id": 6, 
        "catch_copy": "全132邸南向き中心レジデンス", 
        "comment": "横浜市初登場、約12.6haの圧倒的な緑の前に、全132邸・南向き中心のレジデンス", 
        "division_type": 1, 
        "gross_area": "68.48 ～ 83.47m&sup2;", 
        "gross_area_float": 83.47, 
        "houses": "132戸", 
        "houses_int": 132, 
        "image_pc_url": "/image_files/estate_basics/proudtop_pc/00000861/225_140.jpg", 
        "layout": "3LDK ～ 4LDK", 
        "prefecture": "神奈川県", 
        "published_at": 1444058640, 
        "structure_code": "010861", 
        "structure_id": 861, 
        "structure_name": "オハナ戸塚舞岡", 
        "structure_url": "http://www.087sumai.com/totsuka-maioka/"
    }, 
    {
        "access": "東京急行電鉄大井町線尾山台 徒歩6分<br>東京急行電鉄東横線自由が丘 徒歩15分", 
        "access_codes": [
            2323, 
            2321
        ], 
        "access_int": 6, 
        "address": "東京都世田谷区等々力５丁目5番18他（地番）", 
        "area_id": 2, 
        "catch_copy": "城南駅近、自由が丘も徒歩15分", 
        "comment": "東急大井町線「尾山台」駅徒歩6分。世田谷・駅近一戸建て街区、等々力アドレスに誕生。", 
        "division_type": 2, 
        "gross_area": "100.01 ～ 106.42m&sup2;", 
        "gross_area_float": 106.42, 
        "houses": "8戸", 
        "houses_int": 8, 
        "image_pc_url": "/image_files/estate_basics/proudtop_pc/00000854/225_140.jpg", 
        "layout": "3LDK ～ 4LDK", 
        "prefecture": "東京都", 
        "published_at": 1443577680, 
        "structure_code": "010854", 
        "structure_id": 854, 
        "structure_name": "プラウドシーズン等々力", 
        "structure_url": "http://www.proud-web.jp/house/todoroki/"
    }, 
    {
        "access": "ＪＲ京浜東北線北浦和 徒歩3分<br>", 
        "access_codes": [
            2196
        ], 
        "access_int": 3, 
        "address": "埼玉県さいたま市浦和区元町二丁目289番5他（地番）", 
        "area_id": 8, 
        "catch_copy": "駅徒歩3分の私邸。", 
        "comment": "駅徒歩３分、スーパー２分。大通りから一本奥まった地に、全邸南東向きのプライベートレジデンス誕生。", 
        "division_type": 1, 
        "gross_area": "70.00 ～ 72.90m&sup2;", 
        "gross_area_float": 72.9, 
        "houses": "38戸 (内、非分譲住戸1戸（他に管理事務室1戸）)", 
        "houses_int": 38, 
        "image_pc_url": "/image_files/estate_basics/proudtop_pc/00000849/225_140.jpg", 
        "layout": "3LDK ～ 3LDK", 
        "prefecture": "埼玉県", 
        "published_at": 1443577620, 
        "structure_code": "010849", 
        "structure_id": 849, 
        "structure_name": "プラウド北浦和パサージュ", 
        "structure_url": "http://www.proud-web.jp/mansion/kitaurawa-p/"
    }, 
    {
        "access": "ＪＲ総武線津田沼 徒歩8分<br>新京成電鉄新京成線新津田沼 徒歩13分", 
        "access_codes": [
            2199, 
            2256
        ], 
        "access_int": 8, 
        "address": "千葉県習志野市奏の杜一丁目10番1号", 
        "area_id": 7, 
        "catch_copy": "総武線快速＜津田沼＞駅徒歩8分", 
        "comment": "「東京」駅へ直通27分。総武線快速停車「津田沼」駅徒歩8分に誕生する291邸の大規模レジデンス！", 
        "division_type": 1, 
        "gross_area": "67.86 ～ 91.12m&sup2;", 
        "gross_area_float": 91.12, 
        "houses": "291戸 (他に管理室1戸)", 
        "houses_int": 291, 
        "image_pc_url": "/image_files/estate_basics/proudtop_pc/00000846/225_140.jpg", 
        "layout": "2LDK+Ｓ ～ 4LDK", 
        "prefecture": "千葉県", 
        "published_at": 1443577500, 
        "structure_code": "010846", 
        "structure_id": 846, 
        "structure_name": "ザ・レジデンス津田沼奏の杜<br>テラス", 
        "structure_url": "http://www.proud-web.jp/mansion/tsudanuma291"
    }, 
    {
        "access": "ＪＲ京浜東北線南浦和 徒歩7分<br>ＪＲ武蔵野線南浦和 徒歩7分", 
        "access_codes": [
            2196, 
            2176
        ], 
        "access_int": 7, 
        "address": "埼玉県さいたま市南区神明一丁目2番1他（地番）", 
        "area_id": 8, 
        "catch_copy": "文教エリアの静穏な邸宅街。", 
        "comment": "ＪＲ「南浦和」駅徒歩7分。文教エリアの穏やかな住宅街に緑豊かなレジデンス、109邸誕生。南向き中心。", 
        "division_type": 1, 
        "gross_area": "70.01 ～ 84.01m&sup2;", 
        "gross_area_float": 84.01, 
        "houses": "109戸 (非分譲住戸11戸含む、他に管理事務室1戸)", 
        "houses_int": 109, 
        "image_pc_url": "/image_files/estate_basics/proudtop_pc/00000838/225x140.jpg", 
        "layout": "3LDK ～ 4LDK", 
        "prefecture": "埼玉県", 
        "published_at": 1443577440, 
        "structure_code": "010838", 
        "structure_id": 838, 
        "structure_name": "プラウド南浦和神明", 
        "structure_url": "http://www.proud-web.jp/mansion/shinmei/"
    }, 
    {
        "access": "ＪＲ中央線国分寺 徒歩21分、または、バス約5分文化学園大学バス停より 徒歩6分<br>西武鉄道多摩湖線一橋学園 徒歩13分", 
        "access_codes": [
            2184, 
            2286
        ], 
        "access_int": 6, 
        "address": "東京都小平市上水南町一丁目469番46他（地番）", 
        "area_id": 5, 
        "catch_copy": "中央線国分寺、4900万円台～", 
        "comment": "駅北口再開発が進む中央線「国分寺」駅利用。自然の潤い豊かな文教エリアに80邸の大規模戸建て街区誕生。", 
        "division_type": 2, 
        "gross_area": "120.05 ～ 122.10m&sup2;", 
        "gross_area_float": 122.1, 
        "houses": "80戸", 
        "houses_int": 80, 
        "image_pc_url": "/image_files/estate_basics/proudtop_pc/00000837/225_140.jpg", 
        "layout": "4LDK", 
        "prefecture": "東京都", 
        "published_at": 1443577380, 
        "structure_code": "010837", 
        "structure_id": 837, 
        "structure_name": "プラウドシーズン国分寺<br>パークアベニュー", 
        "structure_url": "http://www.proud-web.jp/house/kokubunji80"
    }, 
    {
        "access": "ＪＲ山手線恵比寿 徒歩3分<br>東京メトロ日比谷線恵比寿 徒歩2分", 
        "access_codes": [
            2172, 
            2344
        ], 
        "access_int": 2, 
        "address": "東京都渋谷区恵比寿南一丁目11-4（地番）", 
        "area_id": 1, 
        "catch_copy": "JR「恵比寿」駅徒歩3分。", 
        "comment": "ＪＲ「恵比寿」駅徒歩3分。3ＬＤＫ・80㎡超中心、恵比寿でゆとりという贅を。", 
        "division_type": 1, 
        "gross_area": "54.75 ～ 100.62m&sup2;", 
        "gross_area_float": 100.62, 
        "houses": "50戸 (事業協力者住戸7戸含む)", 
        "houses_int": 50, 
        "image_pc_url": "/image_files/estate_basics/proudtop_pc/00000835/225_140.jpg", 
        "layout": "1LDK ～ 3LDK", 
        "prefecture": "東京都", 
        "published_at": 1443577320, 
        "structure_code": "010835", 
        "structure_id": 835, 
        "structure_name": "プラウド恵比寿南", 
        "structure_url": "http://www.proud-web.jp/mansion/p-ebisuminami/"
    }, 
    {
        "access": "東京急行電鉄田園都市線桜新町 徒歩10分<br>", 
        "access_codes": [
            2324
        ], 
        "access_int": 10, 
        "address": "東京都世田谷区弦巻五丁目598番1・2、599番1・2（地番）", 
        "area_id": 2, 
        "catch_copy": "田園都市線沿線、世田谷区に誕生", 
        "comment": "世田谷区、東急田園都市線「桜新町」。80㎡超中心、ゆとりの広さを備えた174邸の大規模邸宅。", 
        "division_type": 1, 
        "gross_area": "72.14 ～ 110.78m&sup2;", 
        "gross_area_float": 110.78, 
        "houses": "174戸", 
        "houses_int": 174, 
        "image_pc_url": "/image_files/estate_basics/proudtop_pc/00000834/225_140.jpg", 
        "layout": "3LDK ～ 4LDK", 
        "prefecture": "東京都", 
        "published_at": 1443577260, 
        "structure_code": "010834", 
        "structure_id": 834, 
        "structure_name": "プラウド桜新町", 
        "structure_url": "http://www.proud-web.jp/mansion/sakurashinmachi/"
    }, 
    {
        "access": "東武鉄道東武東上線鶴瀬 徒歩11分<br>", 
        "access_codes": [
            2270
        ], 
        "access_int": 11, 
        "address": "埼玉県入間郡三芳町大字藤久保296-8他（地番）", 
        "area_id": 8, 
        "catch_copy": "池袋へ26分、3900万円台～", 
        "comment": "駅徒歩11分、公園を囲む全50邸の大規模戸建て街区。3,900万円台～", 
        "division_type": 2, 
        "gross_area": "114.01 ～ 134.09m&sup2;", 
        "gross_area_float": 134.09, 
        "houses": "50戸", 
        "houses_int": 50, 
        "image_pc_url": "/image_files/estate_basics/proudtop_pc/00000830/225_140.jpg", 
        "layout": "4LDK", 
        "prefecture": "埼玉県", 
        "published_at": 1443577200, 
        "structure_code": "010830", 
        "structure_id": 830, 
        "structure_name": "プラウドシーズン鶴瀬", 
        "structure_url": "http://www.proud-web.jp/house/tsuruse"
    }, 
    {
        "access": "京王電鉄京王線武蔵野台 徒歩10分<br>西武鉄道西武多摩川白糸台 徒歩9分", 
        "access_codes": [
            2301, 
            2287
        ], 
        "access_int": 9, 
        "address": "東京都府中市白糸台三丁目31番45他（地番）", 
        "area_id": 5, 
        "catch_copy": "全戸サービス収納付・4ＬＤＫ", 
        "comment": "府中市の駅近に住まう。都心直結・京王線「武蔵野台」駅徒歩10分。武蔵野に全60邸の大規模街区、誕生。", 
        "division_type": 2, 
        "gross_area": "120.01m&sup2;", 
        "gross_area_float": 120.01, 
        "houses": "39戸", 
        "houses_int": 39, 
        "image_pc_url": "/image_files/estate_basics/proudtop_pc/00000828/225_140.jpg", 
        "layout": "4LDK ～ 4LDK", 
        "prefecture": "東京都", 
        "published_at": 1443577140, 
        "structure_code": "010828", 
        "structure_id": 828, 
        "structure_name": "プラウドシーズン<br>府中武蔵野台（フロント<br>コート）", 
        "structure_url": "http://www.proud-web.jp/house/futyumusashinodai"
    }, 
    {
        "access": "京浜急行電鉄京浜急行線雑色 徒歩12分<br>京浜急行電鉄京浜急行線六郷土手 徒歩10分", 
        "access_codes": [
            2331
        ], 
        "access_int": 10, 
        "address": "東京都大田区西六郷三丁目2-1（A敷地）、1-1（B敷地）（地番）", 
        "area_id": 2, 
        "catch_copy": "東京を自分らしく生きよう。", 
        "comment": "「品川」駅8分「東京」駅15分。敷地面積23,000㎡超・全632邸のビッグプロジェクト、堂々誕生。", 
        "division_type": 1, 
        "gross_area": "64.62 ～ 86.87m&sup2;", 
        "gross_area_float": 86.87, 
        "houses": "632戸", 
        "houses_int": 632, 
        "image_pc_url": "/image_files/estate_basics/proudtop_pc/00000827/225_140.jpg", 
        "layout": "3LDK ～ 4LDK", 
        "prefecture": "東京都", 
        "published_at": 1443577080, 
        "structure_code": "010827", 
        "structure_id": 827, 
        "structure_name": "プラウドシティ大田六郷", 
        "structure_url": "http://www.proud-web.jp/mansion/rokugo/"
    }, 
    {
        "access": "ＪＲ山手線、京浜東北線、高崎線、宇都宮線、常磐線、常磐・成田線上野 徒歩15分<br>東京メトロ日比谷線入谷 徒歩9分", 
        "access_codes": [
            2172, 
            2344
        ], 
        "access_int": 7, 
        "address": "東京都台東区松が谷三丁目382番2（地番）", 
        "area_id": 4, 
        "catch_copy": "「東京」駅へ１駅５分", 
        "comment": "JR「上野」駅徒歩１５分。上野と浅草の“中心”にたたずむ静穏な住宅街に、全邸南向きで誕生。", 
        "division_type": 1, 
        "gross_area": "68.03 ～ 78.04m&sup2;", 
        "gross_area_float": 78.04, 
        "houses": "71戸 (非分譲住戸2戸、非分譲倉庫兼事務所１区画含む、他に管理事務室1戸)", 
        "houses_int": 71, 
        "image_pc_url": "/image_files/estate_basics/proudtop_pc/00000817/225_140.jpg", 
        "layout": "3LDK", 
        "prefecture": "東京都", 
        "published_at": 1443576960, 
        "structure_code": "010817", 
        "structure_id": 817, 
        "structure_name": "プラウド上野松が谷", 
        "structure_url": "http://www.proud-web.jp/mansion/ueno-matsugaya"
    }, 
    {
        "access": "都営地下鉄都営三田線志村三丁目 徒歩7分<br>", 
        "access_codes": [
            2352
        ], 
        "access_int": 7, 
        "address": "東京都板橋区坂下一丁目7-7（地番）", 
        "area_id": 3, 
        "catch_copy": "家族の永住を叶える住環境", 
        "comment": "「大手町」駅直通26分・全戸南向き・生活利便施設充実　[建物完成後より分譲開始]モデルルーム公開中", 
        "division_type": 1, 
        "gross_area": "68.63 ～ 85.80m&sup2;", 
        "gross_area_float": 85.8, 
        "houses": "46戸", 
        "houses_int": 46, 
        "image_pc_url": "/image_files/estate_basics/proudtop_pc/00000792/225_140.jpg", 
        "layout": "3LDK ～ 4LDK", 
        "prefecture": "東京都", 
        "published_at": 1443576840, 
        "structure_code": "010792", 
        "structure_id": 792, 
        "structure_name": "プラウド板橋志村三丁目", 
        "structure_url": "http://www.proud-web.jp/mansion/shimura3/"
    }, 
    {
        "access": "京王電鉄京王線上北沢 徒歩9分<br>京王電鉄京王線桜上水 徒歩14分", 
        "access_codes": [
            2301
        ], 
        "access_int": 9, 
        "address": "東京都世田谷区上北沢１丁目771番2他（地番）", 
        "area_id": 2, 
        "catch_copy": "南向き・75㎡超中心", 
        "comment": "新宿13分。京王線「上北沢」駅徒歩9分。世田谷区に誕生する75㎡超中心のレジデンス。", 
        "division_type": 1, 
        "gross_area": "72.45 ～ 91.95m&sup2;", 
        "gross_area_float": 91.95, 
        "houses": "41戸", 
        "houses_int": 41, 
        "image_pc_url": "/image_files/estate_basics/proudtop_pc/00000774/225_140.jpg", 
        "layout": "3LDK ～ 4LDK", 
        "prefecture": "東京都", 
        "published_at": 1443576780, 
        "structure_code": "010774", 
        "structure_id": 774, 
        "structure_name": "プラウド上北沢ディアージュ", 
        "structure_url": "http://www.proud-web.jp/mansion/kamikitazawa/"
    }, 
    {
        "access": "ＪＲ中央線阿佐ヶ谷 徒歩13分<br>東京メトロ丸ノ内線南阿佐ヶ谷 徒歩5分", 
        "access_codes": [
            2184, 
            2342
        ], 
        "access_int": 5, 
        "address": "東京都杉並区成田東４丁目63番28他（地番）他", 
        "area_id": 3, 
        "catch_copy": "駅徒歩５分｜モデルルーム公開中", 
        "comment": "駅徒歩5分・第一種低層住居専用地域の閑静な住宅地に、杜に包まれる全575邸の邸宅街区誕生。", 
        "division_type": 1, 
        "gross_area": "63.42 ～ 102.71m&sup2; (Ａ：63.42㎡～102.71㎡、B：64.77㎡～90.33㎡)", 
        "gross_area_float": 102.71, 
        "houses": "575戸 (非分譲住戸188戸含む＜A：175戸（45戸）、B：283戸（68戸）、C：76戸（54戸）、D：17戸（2戸）、E：24戸（19戸）　※（）内非分譲住戸数＞)", 
        "houses_int": 575, 
        "image_pc_url": "/image_files/estate_basics/proudtop_pc/00000768/225_140.jpg", 
        "layout": "2LDK ～ 4LDK", 
        "prefecture": "東京都", 
        "published_at": 1443576720, 
        "structure_code": "010768", 
        "structure_id": 768, 
        "structure_name": "プラウドシティ阿佐ヶ谷", 
        "structure_url": "http://www.proud-web.jp/mansion/asagaya/"
    }, 
    {
        "access": "東京メトロ東西線木場 徒歩7分<br>東京メトロ東西線門前仲町 徒歩15分", 
        "access_codes": [
            2345
        ], 
        "access_int": 7, 
        "address": "東京都江東区木場３丁目42番1他（地番）", 
        "area_id": 4, 
        "catch_copy": "大手町駅へ直通７分でアクセス", 
        "comment": "「大手町」駅直通7分。約242,000㎡の都心有数の大型公園を謳歌する、大規模プロジェクト始動。", 
        "division_type": 1, 
        "gross_area": "65.30 ～ 103.78m&sup2;", 
        "gross_area_float": 103.78, 
        "houses": "204戸", 
        "houses_int": 204, 
        "image_pc_url": "/image_files/estate_basics/proudtop_pc/00000760/225_140.jpg", 
        "layout": "2LDK ～ 4LDK", 
        "prefecture": "東京都", 
        "published_at": 1443576660, 
        "structure_code": "010760", 
        "structure_id": 760, 
        "structure_name": "プラウドタワー木場公園", 
        "structure_url": "http://www.proud-web.jp/mansion/kibakouen/"
    }, 
    {
        "access": "ＪＲ埼京線十条 徒歩9分<br>都営地下鉄都営三田線板橋区役所前 徒歩12分", 
        "access_codes": [
            2198, 
            2352
        ], 
        "access_int": 9, 
        "address": "東京都板橋区加賀１丁目3356番47（地番）", 
        "area_id": 3, 
        "catch_copy": "「池袋駅」2駅5分、3キロ圏内", 
        "comment": "「池袋駅」2駅5分、3キロ圏内＆「大手町」駅直通18分。363邸の大規模プロジェクト始動。", 
        "division_type": 1, 
        "gross_area": "73.27 ～ 104.61m&sup2;", 
        "gross_area_float": 104.61, 
        "houses": "363戸", 
        "houses_int": 363, 
        "image_pc_url": "/image_files/estate_basics/proudtop_pc/00000725/225_140.jpg", 
        "layout": "3LDK ～ 4LDK", 
        "prefecture": "東京都", 
        "published_at": 1443576480, 
        "structure_code": "010725", 
        "structure_id": 725, 
        "structure_name": "プラウドシティ加賀学園通り", 
        "structure_url": "http://www.proud-web.jp/mansion/kaga/"
    }, 
    {
        "access": "都営地下鉄都営大江戸線練馬 徒歩13分<br>西武鉄道西武池袋線・豊島線・有楽町線練馬 徒歩14分", 
        "access_codes": [
            2358, 
            2281
        ], 
        "access_int": 12, 
        "address": "東京都練馬区豊玉南三丁目11番1（地番）", 
        "area_id": 3, 
        "catch_copy": "70㎡超、4600万円台～", 
        "comment": "2駅7路線利用可能。ゆとりの全邸70㎡超・南向き中心の全50邸、誕生。", 
        "division_type": 1, 
        "gross_area": "70.80 ～ 85.78m&sup2;", 
        "gross_area_float": 85.78, 
        "houses": "50戸", 
        "houses_int": 50, 
        "image_pc_url": "/image_files/estate_basics/proudtop_pc/00000703/225_140.jpg", 
        "layout": "2LDK+S ～ 3LDK+S", 
        "prefecture": "東京都", 
        "published_at": 1443576420, 
        "structure_code": "010703", 
        "structure_id": 703, 
        "structure_name": "プラウド練馬豊玉イースト", 
        "structure_url": "http://www.proud-web.jp/mansion/toyotama/east/index.html"
    }, 
    {
        "access": "ＪＲ中央線国分寺 徒歩5分<br>", 
        "access_codes": [
            2184
        ], 
        "access_int": 5, 
        "address": "東京都国分寺市南町１丁目316番26、316番38（地番）", 
        "area_id": 5, 
        "catch_copy": "駅徒歩５分、5,900万円台～", 
        "comment": "JR中央線「国分寺」駅徒歩5分。3LDK・5,900万円台～。", 
        "division_type": 1, 
        "gross_area": "70.10 ～ 87.66m&sup2;", 
        "gross_area_float": 87.66, 
        "houses": "125戸 (他に管理事務室1戸)", 
        "houses_int": 125, 
        "image_pc_url": "/image_files/estate_basics/proudtop_pc/00000761/225_140.jpg", 
        "layout": "3LDK ～ 4LDK", 
        "prefecture": "東京都", 
        "published_at": 1443576300, 
        "structure_code": "010761", 
        "structure_id": 761, 
        "structure_name": "プラウド国分寺", 
        "structure_url": "http://www.proud-web.jp/mansion/kokubunji/"
    }, 
    {
        "access": "西武鉄道西武新宿線花小金井 徒歩11分<br>ＪＲ中央線武蔵小金井バス約13分「花小金井五丁目」バス停より 徒歩4分", 
        "access_codes": [
            2284, 
            2184
        ], 
        "access_int": 2, 
        "address": "東京都小平市花小金井２丁目654番42他（地番）", 
        "area_id": 5, 
        "catch_copy": "先着順受付中。5328万円～", 
        "comment": "西武新宿線・急行停車「花小金井」駅徒歩11分。先着順受付中。販売価格5,328万円～", 
        "division_type": 2, 
        "gross_area": "115.10 ～ 120.09m&sup2;", 
        "gross_area_float": 120.09, 
        "houses": "20戸", 
        "houses_int": 20, 
        "image_pc_url": "/image_files/estate_basics/proudtop_pc/00000775/225_140_sky.jpg", 
        "layout": "4LDK ～ 4LDK", 
        "prefecture": "東京都", 
        "published_at": 1443576120, 
        "structure_code": "010775", 
        "structure_id": 775, 
        "structure_name": "プラウドシーズン花小金井<br>コートテラス", 
        "structure_url": "http://www.proud-web.jp/house/hanako2/"
    }, 
    {
        "access": "ＪＲ中央線立川 徒歩10分<br>ＪＲ青梅線立川 徒歩10分", 
        "access_codes": [
            2184, 
            2185
        ], 
        "access_int": 9, 
        "address": "東京都立川市曙町一丁目50番1（地番）他", 
        "area_id": 5, 
        "catch_copy": "駅徒歩10分、80平米超中心", 
        "comment": "立川に、広さという新基準を。80㎡超中心、中央線特快停車「立川」駅利用のゆとりの邸宅、誕生。", 
        "division_type": 1, 
        "gross_area": "80.02 ～ 80.41m&sup2;", 
        "gross_area_float": 80.41, 
        "houses": "66戸 (うち非分譲18戸、他に管理事務室1戸)", 
        "houses_int": 66, 
        "image_pc_url": "/image_files/estate_basics/proudtop_pc/00000767/225_140.jpg", 
        "layout": "3LDK ～ 3LDK", 
        "prefecture": "東京都", 
        "published_at": 1443576060, 
        "structure_code": "010767", 
        "structure_id": 767, 
        "structure_name": "プラウド立川トレサージュ", 
        "structure_url": "http://www.proud-web.jp/mansion/tachikawa/"
    }, 
    {
        "access": "ＪＲ中央線武蔵小金井バス約8分「日立国際電気前」バス停より 徒歩6分<br>西武鉄道西武新宿線花小金井 徒歩20分、または、バス約7分「鈴の木台」バス停より 徒歩5分", 
        "access_codes": [
            2184, 
            2284
        ], 
        "access_int": 5, 
        "address": "東京都小平市鈴木町１丁目390-35他（地番）", 
        "area_id": 5, 
        "catch_copy": "4ＬＤＫ　4889万円台～", 
        "comment": "予定販売価格4,800万円台～　土地面積全邸120㎡超　全107区画のビッグタウン", 
        "division_type": 2, 
        "gross_area": "120.09 ～ 125.15m&sup2;", 
        "gross_area_float": 125.15, 
        "houses": "107戸", 
        "houses_int": 107, 
        "image_pc_url": "/image_files/estate_basics/proudtop_pc/00000736/225_140.jpg", 
        "layout": "4LDK ～ 4LDK", 
        "prefecture": "東京都", 
        "published_at": 1443575940, 
        "structure_code": "010736", 
        "structure_id": 736, 
        "structure_name": "プラウドシーズン武蔵小金井<br>ガーデンアベニュー", 
        "structure_url": "http://www.proud-web.jp/house/musashikoganeiga/"
    }, 
    {
        "access": "小田急電鉄小田急線町田 徒歩6分<br>ＪＲ横浜線町田 徒歩7分", 
        "access_codes": [
            2311, 
            2177
        ], 
        "access_int": 6, 
        "address": "東京都町田市原町田五丁目278番1（地番）", 
        "area_id": 5, 
        "catch_copy": "駅徒歩６分｜モデルルーム公開中", 
        "comment": "小田急線「町田」駅 徒歩6分、フラットアプローチ。大通りから一本入った地。", 
        "division_type": 1, 
        "gross_area": "55.64 ～ 75.34m&sup2;", 
        "gross_area_float": 75.34, 
        "houses": "49戸", 
        "houses_int": 49, 
        "image_pc_url": "/image_files/estate_basics/proudtop_pc/00000732/225_140.jpg", 
        "layout": "2LDK ～ 3LDK", 
        "prefecture": "東京都", 
        "published_at": 1443575880, 
        "structure_code": "010732", 
        "structure_id": 732, 
        "structure_name": "プラウド町田マークス", 
        "structure_url": "http://www.proud-web.jp/mansion/haramachida/"
    }, 
    {
        "access": "京王電鉄京王線つつじヶ丘 徒歩11分<br>京王電鉄京王線柴崎 徒歩7分", 
        "access_codes": [
            2301
        ], 
        "access_int": 7, 
        "address": "東京都調布市菊野台三丁目53番126 他（地番）", 
        "area_id": 5, 
        "catch_copy": "野川・小学校隣接。先着順受付中", 
        "comment": "新宿直通17分、急行停車。野川隣接の自然豊かな一戸建て、全51邸。", 
        "division_type": 2, 
        "gross_area": "120.09 ～ 124.86m&sup2;", 
        "gross_area_float": 124.86, 
        "houses": "51戸", 
        "houses_int": 51, 
        "image_pc_url": "/image_files/estate_basics/proudtop_pc/00000717/225_140.jpg", 
        "layout": "4LDK", 
        "prefecture": "東京都", 
        "published_at": 1443575820, 
        "structure_code": "010717", 
        "structure_id": 717, 
        "structure_name": "プラウドシーズンつつじヶ丘", 
        "structure_url": "http://www.proud-web.jp/house/ttj/"
    }, 
    {
        "access": "京王電鉄相模原線稲城 徒歩6分<br>ＪＲ南武線稲城長沼 徒歩21分", 
        "access_codes": [
            2303, 
            2174
        ], 
        "access_int": 6, 
        "address": "東京都稲城市大字東長沼字八号2416番の一部　外32筆、2447番の一部　外19筆（地番）", 
        "area_id": 5, 
        "catch_copy": "新宿へ23分。3900万円台〜", 
        "comment": "新宿・渋谷へ23分。駅徒歩６分。商業・小学校・保育園・公園が徒歩圏の新しい街に、全412邸誕生。", 
        "division_type": 1, 
        "gross_area": "71.94 ～ 97.35m&sup2;", 
        "gross_area_float": 97.35, 
        "houses": "412戸", 
        "houses_int": 412, 
        "image_pc_url": "/image_files/estate_basics/proudtop_pc/00000714/225_140.jpg", 
        "layout": "3LDK ～ 4LDK", 
        "prefecture": "東京都", 
        "published_at": 1443575760, 
        "structure_code": "010714", 
        "structure_id": 714, 
        "structure_name": "プラウドシティ南山", 
        "structure_url": "http://www.proud-web.jp/mansion/minamiyama/"
    }, 
    {
        "access": "西武鉄道西武新宿線花小金井 徒歩17分<br>ＪＲ中央線武蔵小金井バス約13分「花小金井五丁目」バス停より 徒歩3分", 
        "access_codes": [
            2284, 
            2184
        ], 
        "access_int": 3, 
        "address": "東京都小平市花小金井４丁目213番77他（地番）", 
        "area_id": 5, 
        "catch_copy": "家具付きモデルハウス商談会開催", 
        "comment": "山手線まで直通4駅21分。中央線・池袋線も利用可。大きい！歩ける！戸建プロジェクト誕生。", 
        "division_type": 2, 
        "gross_area": "120.10 ～ 121.13m&sup2;", 
        "gross_area_float": 121.13, 
        "houses": "80戸", 
        "houses_int": 80, 
        "image_pc_url": "/image_files/estate_basics/proudtop_pc/00000681/225_140.jpg", 
        "layout": "4LDK", 
        "prefecture": "東京都", 
        "published_at": 1443575700, 
        "structure_code": "010681", 
        "structure_id": 681, 
        "structure_name": "プラウドシーズン花小金井<br>ガーデンテラス", 
        "structure_url": "http://www.proud-web.jp/house/hanako/"
    }, 
    {
        "access": "小田急電鉄小田急多摩線栗平 徒歩9分<br>小田急電鉄小田急小田原線新百合ヶ丘バス約11分上平尾バス停より 徒歩1分", 
        "access_codes": [
            2313, 
            2311
        ], 
        "access_int": 1, 
        "address": "東京都稲城市平尾字十号1163番地1他（地番）", 
        "area_id": 5, 
        "catch_copy": "新百合ヶ丘生活圏。南ひな壇邸宅", 
        "comment": "『新百合ヶ丘』生活圏。駅徒歩９分の南ひな壇の地に、全２５０区画・大規模一戸建て街区が誕生。", 
        "division_type": 2, 
        "gross_area": "135.19 ～ 136.14m&sup2;", 
        "gross_area_float": 136.14, 
        "houses": "250戸", 
        "houses_int": 250, 
        "image_pc_url": "/image_files/estate_basics/proudtop_pc/00000675/225_140.jpg", 
        "layout": "4LDK", 
        "prefecture": "東京都", 
        "published_at": 1443575640, 
        "structure_code": "010675", 
        "structure_id": 675, 
        "structure_name": "プラウドシーズン栗平", 
        "structure_url": "http://www.proud-web.jp/house/kurihira/"
    }, 
    {
        "access": "京王電鉄京王線仙川 徒歩7分<br>京王電鉄京王線つつじヶ丘 徒歩10分", 
        "access_codes": [
            2301
        ], 
        "access_int": 7, 
        "address": "東京都調布市仙川町２丁目6番5（地番）", 
        "area_id": 5, 
        "catch_copy": "棟内モデルルーム好評公開中", 
        "comment": "京王線「仙川」駅徒歩7分の大規模レジデンス。閑静な住宅街に面した「カームコート」ご紹介中", 
        "division_type": 1, 
        "gross_area": "75.12 ～ 77.17m&sup2;", 
        "gross_area_float": 77.17, 
        "houses": "275戸 (他に管理事務室1戸)", 
        "houses_int": 275, 
        "image_pc_url": "/image_files/estate_basics/proudtop_pc/00000620/225_140.jpg", 
        "layout": "2LDK+S ～ 3LDK", 
        "prefecture": "東京都", 
        "published_at": 1443575580, 
        "structure_code": "010620", 
        "structure_id": 620, 
        "structure_name": "プラウドシティ仙川", 
        "structure_url": "http://www.proud-web.jp/mansion/sengawa/"
    }, 
    {
        "access": "ＪＲ南武線武蔵中原 徒歩9分<br>", 
        "access_codes": [
            2174
        ], 
        "access_int": 9, 
        "address": "神奈川県川崎市中原区上小田中七丁目1541-1他（地番）", 
        "area_id": 6, 
        "catch_copy": "南・南東向き70㎡超", 
        "comment": "「武蔵中原」駅徒歩9分。武蔵小杉エリア1.3ｋｍ圏。緑と利便が出会う、豊潤な地に誕生する89邸。", 
        "division_type": 1, 
        "gross_area": "70.78 ～ 87.78m&sup2;", 
        "gross_area_float": 87.78, 
        "houses": "89戸", 
        "houses_int": 89, 
        "image_pc_url": "/image_files/estate_basics/proudtop_pc/00000841/225_140.jpg", 
        "layout": "3LDK ～ 4LDK", 
        "prefecture": "神奈川県", 
        "published_at": 1443575520, 
        "structure_code": "010841", 
        "structure_id": 841, 
        "structure_name": "プラウド武蔵中原<br>トレサージュ", 
        "structure_url": "http://www.proud-web.jp/mansion/musasi-nakahara89/"
    }, 
    {
        "access": "東京急行電鉄東横線・目黒線日吉 徒歩14分<br>横浜市交通局横浜市営地下鉄グリーンライン日吉 徒歩14分", 
        "access_codes": [
            2321, 
            2374
        ], 
        "access_int": 14, 
        "address": "神奈川県横浜市港北区箕輪町二丁目785番（地番）", 
        "area_id": 6, 
        "catch_copy": "東横線沿線、全邸南南西向き", 
        "comment": "東急東横線・通勤特急停車「日吉」駅。緑と造形の大規模レジデンス・全177邸、誕生。", 
        "division_type": 1, 
        "gross_area": "71.31 ～ 87.20m&sup2;", 
        "gross_area_float": 87.2, 
        "houses": "177戸", 
        "houses_int": 177, 
        "image_pc_url": "/image_files/estate_basics/proudtop_pc/00000831/225_140.jpg", 
        "layout": "3LDK ～ 4LDK", 
        "prefecture": "神奈川県", 
        "published_at": 1443575460, 
        "structure_code": "010831", 
        "structure_id": 831, 
        "structure_name": "プラウド日吉", 
        "structure_url": "http://www.proud-web.jp/mansion/hiyoshi/"
    }, 
    {
        "access": "東京急行電鉄田園都市線宮崎台 徒歩2分<br>", 
        "access_codes": [
            2324
        ], 
        "access_int": 2, 
        "address": "神奈川県川崎市宮前区宮崎二丁目9-2他（地番）", 
        "area_id": 6, 
        "catch_copy": "駅徒歩2分、全邸南東向き。", 
        "comment": "田園都市線「宮崎台」駅徒歩2分。駅前の丘に、新たなランドマークレジデンス誕生。", 
        "division_type": 1, 
        "gross_area": "68.12 ～ 75.62m&sup2;", 
        "gross_area_float": 75.62, 
        "houses": "88戸", 
        "houses_int": 88, 
        "image_pc_url": "/image_files/estate_basics/proudtop_pc/00000823/225_140.jpg", 
        "layout": "3LDK", 
        "prefecture": "神奈川県", 
        "published_at": 1443575400, 
        "structure_code": "010823", 
        "structure_id": 823, 
        "structure_name": "プラウド宮崎台フロント", 
        "structure_url": "http://www.proud-web.jp/mansion/p-miyazakidai88/"
    }, 
    {
        "access": "ＪＲ横浜線淵野辺 徒歩10分<br>ＪＲ横浜線矢部 徒歩10分", 
        "access_codes": [
            2177
        ], 
        "access_int": 10, 
        "address": "神奈川県相模原市中央区淵野辺２丁目133番379（道路負担部分：神奈川県相模原市淵野辺二丁目133番6）", 
        "area_id": 6, 
        "catch_copy": "全516邸、南向きの大規模開発", 
        "comment": "大規模プロジェクト！！3LDK2,400万円台より、4LDK3,100万円台より、全邸南向き配棟計画", 
        "division_type": 1, 
        "gross_area": "68.46 ～ 80.01m&sup2;", 
        "gross_area_float": 80.01, 
        "houses": "298戸 (全体戸数516戸（仮称・第2工区 218戸、他に管理事務室1戸、ゲストルーム1戸、集会室等5戸）)", 
        "houses_int": 298, 
        "image_pc_url": "/image_files/estate_basics/proudtop_pc/00000809/淵野辺225_140.jpg", 
        "layout": "3LDK ・ 4LDK", 
        "prefecture": "神奈川県", 
        "published_at": 1443575340, 
        "structure_code": "010809", 
        "structure_id": 809, 
        "structure_name": "オハナ淵野辺ガーデニア　<br>ファーストステージ", 
        "structure_url": "http://www.087sumai.com/fuchinobe/"
    }, 
    {
        "access": "東京急行電鉄田園都市線市が尾 徒歩11分<br>", 
        "access_codes": [
            2324
        ], 
        "access_int": 11, 
        "address": "神奈川県横浜市青葉区荏田西４丁目1-32（地番）", 
        "area_id": 6, 
        "catch_copy": "東急田園都市線、駅徒歩11分～", 
        "comment": "田園都市線「市が尾」駅徒歩11分。横浜市青葉区の成熟した住宅地に佇む“美しき丘の邸宅街”誕生。", 
        "division_type": 2, 
        "gross_area": "129.97 ～ 130.01m&sup2;", 
        "gross_area_float": 130.01, 
        "houses": "12戸", 
        "houses_int": 12, 
        "image_pc_url": "/image_files/estate_basics/proudtop_pc/00000788/225_140.jpg", 
        "layout": "4LDK", 
        "prefecture": "神奈川県", 
        "published_at": 1443575280, 
        "structure_code": "010788", 
        "structure_id": 788, 
        "structure_name": "プラウドシーズン青葉荏田西", 
        "structure_url": "http://www.proud-web.jp/house/aobaedanishi/"
    }, 
    {
        "access": "東京急行電鉄田園都市線宮崎台 徒歩6分<br>", 
        "access_codes": [
            2324
        ], 
        "access_int": 6, 
        "address": "神奈川県川崎市宮前区宮前平3丁目8－1他（地番）", 
        "area_id": 6, 
        "catch_copy": "ゆとりの広さの大規模レジデンス", 
        "comment": "田園都市線駅徒歩6分。世界的構想から生まれた”田都”の玄関口に全429邸の大規模レジデンス誕生", 
        "division_type": 1, 
        "gross_area": "59.23 ～ 92.30m&sup2;", 
        "gross_area_float": 92.3, 
        "houses": "225戸 (ウエストコート)", 
        "houses_int": 225, 
        "image_pc_url": "/image_files/estate_basics/proudtop_pc/00000784/225_140.jpg", 
        "layout": "2LDK ～ 4LDK", 
        "prefecture": "神奈川県", 
        "published_at": 1443575220, 
        "structure_code": "010784", 
        "structure_id": 784, 
        "structure_name": "プラウドシティ宮崎台", 
        "structure_url": "http://www.proud-web.jp/mansion/pc-miyazakidai/"
    }, 
    {
        "access": "北総鉄道北総線小室 徒歩4分<br>", 
        "access_codes": [
            2257
        ], 
        "access_int": 4, 
        "address": "千葉県船橋市小室町5277番地 他", 
        "area_id": 7, 
        "catch_copy": "駅徒歩４分。2,900万円台～", 
        "comment": "駅徒歩4分。日本橋・品川直結。全331戸の都市型一戸建て。2,900万円台～", 
        "division_type": 2, 
        "gross_area": "135.50 ～ 145.21m&sup2;", 
        "gross_area_float": 145.21, 
        "houses": "331戸", 
        "houses_int": 331, 
        "image_pc_url": "/image_files/estate_basics/proudtop_pc/00000656/225_140.jpg", 
        "layout": "4LDK ～ 4LDK", 
        "prefecture": "千葉県", 
        "published_at": 1443575160, 
        "structure_code": "010656", 
        "structure_id": 656, 
        "structure_name": "プラウドシーズン船橋小室", 
        "structure_url": "http://www.proud-web.jp/house/komuro/"
    }, 
    {
        "access": "ＪＲ京葉線検見川浜 徒歩7分<br>", 
        "access_codes": [
            2164
        ], 
        "access_int": 7, 
        "address": "千葉県千葉市美浜区磯辺五丁目52番1", 
        "area_id": 7, 
        "catch_copy": "スーパー直結。全戸南東南西向き", 
        "comment": "ＪＲ京葉線快速停車「検見川浜」駅徒歩7分。スーパー直結の全戸南東・南西向き５４５邸大規模マンション。", 
        "division_type": 1, 
        "gross_area": "70.58 ～ 99.20m&sup2;", 
        "gross_area_float": 99.2, 
        "houses": "545戸", 
        "houses_int": 545, 
        "image_pc_url": "/image_files/estate_basics/proudtop_pc/00000819/225_140.jpg", 
        "layout": "3LDK ～ 4LDK", 
        "prefecture": "千葉県", 
        "published_at": 1443575100, 
        "structure_code": "010819", 
        "structure_id": 819, 
        "structure_name": "ザ・レジデンス検見川浜<br>ガーデンズ", 
        "structure_url": "http://www.proud-web.jp/mansion/kemigawahama545/"
    }, 
    {
        "access": "東葉高速鉄道東葉高速線北習志野 徒歩13分<br>新京成電鉄新京成線北習志野 徒歩14分", 
        "access_codes": [
            2395, 
            2256
        ], 
        "access_int": 13, 
        "address": "千葉県船橋市習志野台６丁目3-2", 
        "area_id": 7, 
        "catch_copy": "東西線直結、大手町駅33分！", 
        "comment": "3LDK2,700万円台より。東西線直結、大手町駅33分！ 2路線利用可。全241邸、大規模開発。", 
        "division_type": 1, 
        "gross_area": "71.39 ～ 88.83m&sup2;", 
        "gross_area_float": 88.83, 
        "houses": "241戸 (他に管理事務室1戸、集会室等1戸)", 
        "houses_int": 241, 
        "image_pc_url": "/image_files/estate_basics/proudtop_pc/00000778/北習志野225_140.jpg", 
        "layout": "3LDK ・ 4LDK", 
        "prefecture": "千葉県", 
        "published_at": 1443575040, 
        "structure_code": "010778", 
        "structure_id": 778, 
        "structure_name": "オハナ北習志野", 
        "structure_url": "http://www.087sumai.com/kitanarashino/"
    }, 
    {
        "access": "ＪＲ埼京線武蔵浦和 徒歩3分<br>ＪＲ武蔵野線武蔵浦和 徒歩3分", 
        "access_codes": [
            2198, 
            2176
        ], 
        "access_int": 3, 
        "address": "埼玉県さいたま市南区別所七丁目239番（地番）", 
        "area_id": 8, 
        "catch_copy": "免震×長期優良住宅×子育て認定", 
        "comment": "JR埼京線・武蔵野線の2路線アクセス、快速や始発も利用可能。武蔵浦和駅第1街区、最終プロジェクト始動", 
        "division_type": 1, 
        "gross_area": "60.82 ～ 86.17m&sup2;", 
        "gross_area_float": 86.17, 
        "houses": "165戸", 
        "houses_int": 165, 
        "image_pc_url": "/image_files/estate_basics/proudtop_pc/00000822/225_140.jpg", 
        "layout": "2LDK ～ 4LDK", 
        "prefecture": "埼玉県", 
        "published_at": 1443574980, 
        "structure_code": "010822", 
        "structure_id": 822, 
        "structure_name": "プラウドタワー武蔵浦和<br>レジデンス", 
        "structure_url": "http://www.proud-web.jp/mansion/musashiurawa/"
    }, 
    {
        "access": "ＪＲ埼京線中浦和 徒歩4分<br>ＪＲ京浜東北線・東北本線（宇都宮線）・高崎線・湘南新宿ライン浦和国際興業バス【浦11】「浦和駅西口」から「中浦和駅」停留所へバス約9分「中浦和駅」停留所から現地までバス停より 徒歩4分", 
        "access_codes": [
            2198, 
            2196
        ], 
        "access_int": 4, 
        "address": "埼玉県さいたま市南区鹿手袋２丁目801番1他（地番）", 
        "area_id": 8, 
        "catch_copy": "駅徒歩4分。駅近の邸宅地。", 
        "comment": "駅徒歩4分。「別所沼公園」の自然を享受できる地に豊富なプランをご用意した全42邸、誕生。", 
        "division_type": 1, 
        "gross_area": "69.22 ～ 84.20m&sup2;", 
        "gross_area_float": 84.2, 
        "houses": "42戸 (他に管理事務室1戸)", 
        "houses_int": 42, 
        "image_pc_url": "/image_files/estate_basics/proudtop_pc/00000757/225_140.jpg", 
        "layout": "3LDK ・ 4LDK", 
        "prefecture": "埼玉県", 
        "published_at": 1443574920, 
        "structure_code": "010757", 
        "structure_id": 757, 
        "structure_name": "プラウド別所沼公園<br>トレサージュ", 
        "structure_url": "http://www.proud-web.jp/mansion/bessyonumakouen3/"
    }, 
    {
        "access": "東武鉄道東武東上線志木 徒歩4分<br>", 
        "access_codes": [
            2270
        ], 
        "access_int": 4, 
        "address": "埼玉県志木市本町５丁目2119番21（地番）", 
        "area_id": 8, 
        "catch_copy": "駅徒歩4分。402邸の複合開発", 
        "comment": "駅徒歩4分、スーパー直結、全邸70㎡超。急行停車「志木」駅に、402邸の複合開発プロジェクト誕生！", 
        "division_type": 1, 
        "gross_area": "71.05 ～ 87.85m&sup2;", 
        "gross_area_float": 87.85, 
        "houses": "402戸 (他に管理事務室1戸)", 
        "houses_int": 402, 
        "image_pc_url": "/image_files/estate_basics/proudtop_pc/00000744/225_140.jpg", 
        "layout": "3LDK ～ 4LDK", 
        "prefecture": "埼玉県", 
        "published_at": 1443574800, 
        "structure_code": "010744", 
        "structure_id": 744, 
        "structure_name": "プラウドシティ志木本町", 
        "structure_url": "http://www.proud-web.jp/mansion/shiki402/"
    }
]